nia_etl_utils/__init__.py
nia_etl_utils/config.py
nia_etl_utils/database.py
nia_etl_utils/email_smtp.py
nia_etl_utils/env_config.py
nia_etl_utils/exceptions.py
nia_etl_utils/limpeza_pastas.py
nia_etl_utils/logger_config.py
nia_etl_utils/processa_csv.py
nia_etl_utils/processa_csv_paralelo.py
nia_etl_utils/results.py
nia_etl_utils-0.2.0.dist-info/METADATA
nia_etl_utils-0.2.0.dist-info/WHEEL
nia_etl_utils-0.2.0.dist-info/top_level.txt
nia_etl_utils-0.2.0.dist-info/RECORD
