Metadata-Version: 2.4
Name: nia-etl-utils
Version: 0.2.0
Summary: Utilitários compartilhados para pipelines ETL do NIA/MPRJ
Author-email: Nícolas Esmael <nicolas.esmael@mprj.mp.br>
License: MIT
Project-URL: Repository, https://gitlab-dti.mprj.mp.br/nia/etl-nia/nia-etl-utils
Project-URL: Documentation, https://gitlab-dti.mprj.mp.br/nia/etl-nia/nia-etl-utils/-/blob/main/README.md
Project-URL: Changelog, https://gitlab-dti.mprj.mp.br/nia/etl-nia/nia-etl-utils/-/blob/main/CHANGELOG.md
Keywords: etl,data-engineering,pipeline,mprj,nia
Classifier: Development Status :: 4 - Beta
Classifier: Intended Audience :: Developers
Classifier: License :: OSI Approved :: MIT License
Classifier: Operating System :: OS Independent
Classifier: Programming Language :: Python :: 3
Classifier: Programming Language :: Python :: 3.10
Classifier: Programming Language :: Python :: 3.11
Classifier: Programming Language :: Python :: 3.12
Classifier: Programming Language :: Python :: 3.13
Classifier: Topic :: Database
Classifier: Topic :: Software Development :: Libraries :: Python Modules
Classifier: Typing :: Typed
Requires-Python: >=3.10
Requires-Dist: loguru>=0.7.0
Requires-Dist: python-dotenv>=1.0.0
Requires-Dist: cx-Oracle>=8.3.0
Requires-Dist: psycopg2-binary>=2.9.0
Requires-Dist: sqlalchemy>=2.0.0
Requires-Dist: pandas>=2.0.0
Provides-Extra: dev
Requires-Dist: pytest>=7.0.0; extra == "dev"
Requires-Dist: pytest-cov>=4.0.0; extra == "dev"
Requires-Dist: ruff>=0.1.0; extra == "dev"
Requires-Dist: mypy>=1.0.0; extra == "dev"
Requires-Dist: pandas-stubs>=2.0.0; extra == "dev"
Provides-Extra: docs
Requires-Dist: mkdocs>=1.5.0; extra == "docs"
Requires-Dist: mkdocs-material>=9.0.0; extra == "docs"
Requires-Dist: mkdocstrings[python]>=0.24.0; extra == "docs"
